{"escapees":{"humans":{"1":{"name":"Baam Frest","ckey":"gabrieldoombr","location":"Emergency Shuttle","health":64,"job":"Station Engineer","species":"Human"},"2":{"name":"Dante Afonso","ckey":"darksucc","location":"Emergency Shuttle","health":13.04,"job":"Security Officer","species":"Papa John's Pizza"},"3":{"name":"Florian Ramis","ckey":"aert","location":"Emergency Shuttle","health":-19.1,"job":"Warden","species":"Papa John's Pizza"},"4":{"name":"Florian Ramis","ckey":"arthurlopesgd","location":"Emergency Shuttle","health":5.25,"job":"Security Officer","species":"Human"},"5":{"name":"Georg Hau","ckey":"giva","location":"Emergency Shuttle","health":-223.47,"job":"Bartender","species":"Human"},"6":{"name":"Juliana Barrois","ckey":"alucard181","location":"Emergency Shuttle","health":43.57,"job":"Unassigned","species":"Human"},"7":{"name":"Oui Oui","ckey":"manu9123","location":"Emergency Shuttle","health":-1.62,"job":"Mime","species":"Synthetic"},"8":{"name":"Shinji Ikari","ckey":"hue100","location":"Emergency Shuttle","health":43.63,"job":"Roboticist","species":"Human"}},"silicons":[],"others":{"1":{"name":"illusion","ckey":"iunknow","location":"Ghost Cafe","health":100,"name":"illusion","typepath":"/mob/living/simple_animal/hostile/illusion/escape"}},"npcs":{"Cayenne":1,"chicken":3,"Cleanbot":1,"cow":1,"Medibot":4,"monkey":3,"Syndicate Operative":4,"The Ghost of Poly":1}},"abandoned":{"humans":[],"silicons":[],"others":{"1":{"name":"Dina Coldplay","ckey":"iunknow","location":"Cloning Lab","health":100,"name":"Dina Coldplay","typepath":"/mob/living/brain"}},"npcs":{"Pun Pun":1,"Medibot":3,"Artificer":6,"ash drake":3,"cow":1,"blood-drunk miner":3,"Bumbles":1,"butterfly":4,"Unknown":17,"Citrus":1,"Cleanbot":5,"coder monkey":9,"crab":6,"dwarf legion":1,"creature":1,"familiar gorilla":1,"chicken":2,"Floorbot":1,"Goat Pope":1,"goldgrub":3,"goliath":11,"goose":1,"grey baby slime (123)":3,"gubbuck":1,"guthen":1,"hierophant":1,"Ian":1,"Juggernaut":8,"Kawaii Shark":1,"king of the goats":1,"lava imp":8,"Legion":1,"legion":22,"Lizard":2,"monkey":8,"mouse":4,"MULEbot":2,"Mysterious Medibot":1,"Officer Pingsky":1,"opossum":3,"goat":1,"Poly":1,"Officer Beep O'sky":2,"pug":1,"Rogue Process":1,"Runtime":1,"shambling miner":12,"slime corgi puppy":1,"Swarmer":30,"swarmer beacon":1,"The Gladiator":1,"watcher":21,"Wraith":4}},"ghosts":{"1":{"name":"a swarmer","ckey":"maconha0420"},"2":{"name":"Lolly Mwangi","ckey":"graubergames"},"3":{"name":"Georg Hau","ckey":"giva"}},"additional data":{"station integrity":90.8}}
